pokepy_sdk/__init__.py
pokepy_sdk/exceptions.py
pokepy_sdk/src/client.py
pokepy_sdk/src/models/generation.py
pokepy_sdk/src/models/pokemon.py
pokepy_sdk/tests/data/sample_pokemon_response.json
pokepy_sdk/tests/integration_tests.py
pokepy_sdk/tests/models/test_generation.py
pokepy_sdk/tests/models/test_pokemon.py
pokepy_sdk/tests/test_client.py
pokepy_sdk-0.1.0.dist-info/METADATA
pokepy_sdk-0.1.0.dist-info/WHEEL
pokepy_sdk-0.1.0.dist-info/RECORD
