Metadata-Version: 2.1
Name: pokepy-sdk
Version: 0.1.0
Summary: Python library for interacting with the `pokeapi` API
License: MIT
Author: Your Name
Author-email: john1091w@gmail.com
Requires-Python: >=3.8,<4.0
Classifier: License :: OSI Approved :: MIT License
Classifier: Programming Language :: Python :: 3
Classifier: Programming Language :: Python :: 3.8
Classifier: Programming Language :: Python :: 3.9
Classifier: Programming Language :: Python :: 3.10
Classifier: Programming Language :: Python :: 3.11
Classifier: Programming Language :: Python :: 3.12
Requires-Dist: black (>=24.8.0,<25.0.0)
Requires-Dist: mypy (>=1.11.2,<2.0.0)
Requires-Dist: pathlib (>=1.0.1,<2.0.0)
Requires-Dist: pydantic (>=2.9.2,<3.0.0)
Requires-Dist: pytest (>=8.3.3,<9.0.0)
Requires-Dist: requests (>=2.32.3,<3.0.0)
Requires-Dist: ruff (>=0.6.7,<0.7.0)
Requires-Dist: tenacity (>=9.0.0,<10.0.0)
